endt/__init__.py
endt/data.py
endt/func.py
endt-0.11.1.dist-info/METADATA
endt-0.11.1.dist-info/WHEEL
endt-0.11.1.dist-info/top_level.txt
endt-0.11.1.dist-info/RECORD
