Metadata-Version: 2.4
Name: endt
Version: 0.11.1
Summary: Enhanced Decision Tree
Author-email: Alexander Ershov <fiaf1@mail.ru>
Project-URL: Homepage, https://gitlab.com/nanoworld_ml/enhanceddecisiontree
Project-URL: Bug Tracker, https://gitlab.com/nanoworld_ml/enhanceddecisiontree/-/issues
Classifier: Development Status :: 3 - Alpha
Classifier: Programming Language :: Python :: 3
Classifier: License :: OSI Approved :: GNU General Public License v3 or later (GPLv3+)
Classifier: Operating System :: POSIX
Classifier: Operating System :: Unix
Classifier: Intended Audience :: Developers
Classifier: Intended Audience :: Science/Research
Classifier: Topic :: System :: Distributed Computing
Requires-Python: >=3.10
Requires-Dist: numpy
Requires-Dist: scipy
